AUTHORS.rst
CHANGELOG.rst
CONTRIBUTING.rst
LICENSE
MANIFEST.in
README.rst
requirements.in
setup.cfg
setup.py
versioneer.py
docs/Makefile
docs/authors.rst
docs/conf.py
docs/contributing.rst
docs/history.rst
docs/index.rst
docs/installation.rst
docs/make.bat
docs/readme.rst
docs/usage.rst
imessage_extractor/__init__.py
imessage_extractor/_version.py
imessage_extractor/cli.py
imessage_extractor.egg-info/PKG-INFO
imessage_extractor.egg-info/SOURCES.txt
imessage_extractor.egg-info/dependency_links.txt
imessage_extractor.egg-info/entry_points.txt
imessage_extractor.egg-info/not-zip-safe
imessage_extractor.egg-info/requires.txt
imessage_extractor.egg-info/top_level.txt
imessage_extractor/graphics/about.png
imessage_extractor/graphics/imessage_extractor_logo.png
imessage_extractor/graphics/imessage_logo.png
imessage_extractor/graphics/imessage_visualizer_logo.png
imessage_extractor/graphics/my_stats.png
imessage_extractor/graphics/pick_a_contact.png
imessage_extractor/graphics/repository_open_graph.png
imessage_extractor/graphics/rocket.gif
imessage_extractor/graphics/source_code.png
imessage_extractor/src/.DS_Store
imessage_extractor/src/README.rst
imessage_extractor/src/go.py
imessage_extractor/src/__pycache__/go.cpython-39.pyc
imessage_extractor/src/__pycache__/refresh_contacts.cpython-39.pyc
imessage_extractor/src/app/.DS_Store
imessage_extractor/src/app/app.py
imessage_extractor/src/app/color_theme.py
imessage_extractor/src/app/helpers.py
imessage_extractor/src/app/run_app.py
imessage_extractor/src/app/stylesheet.css
imessage_extractor/src/app/.streamlit/config.toml
imessage_extractor/src/app/__pycache__/color_theme.cpython-39.pyc
imessage_extractor/src/app/__pycache__/helpers.cpython-39.pyc
imessage_extractor/src/app/__pycache__/run_app.cpython-39.pyc
imessage_extractor/src/app/data/extract.py
imessage_extractor/src/app/data/manifest.json
imessage_extractor/src/app/data/__pycache__/extract.cpython-39.pyc
imessage_extractor/src/app/pages/.DS_Store
imessage_extractor/src/app/pages/about.py
imessage_extractor/src/app/pages/home.py
imessage_extractor/src/app/pages/my_stats.py
imessage_extractor/src/app/pages/pick_a_contact.py
imessage_extractor/src/app/pages/__pycache__/about.cpython-39.pyc
imessage_extractor/src/app/pages/__pycache__/home.cpython-39.pyc
